markerbci/__init__.py
markerbci/buttonbox/__init__.py
markerbci/buttonbox/buttonbox.py
markerbci/buttonbox/extended.py
markerbci/buttonbox/joystick.py
markerbci/buttonbox/utils.py
markerbci-0.0.7.dist-info/LICENSE
markerbci-0.0.7.dist-info/METADATA
markerbci-0.0.7.dist-info/WHEEL
markerbci-0.0.7.dist-info/top_level.txt
markerbci-0.0.7.dist-info/RECORD
