Metadata-Version: 2.1
Name: markerbci
Version: 0.0.7
Summary: Handling marker devices for brain-computer interfaces.
Home-page: https://github.com/simonkojima/markerbci-python
Author: Simon Kojima
Author-email: simon.kojima@outlook.com
Project-URL: Bug Tracker, https://github.com/simonkojima/markerbci-python/issues
Classifier: Programming Language :: Python :: 3
Classifier: License :: OSI Approved :: MIT License
Classifier: Operating System :: OS Independent
Requires-Python: >=2.6
License-File: LICENSE
